LICENSE
README.md
setup.py
libcflib/__init__.py
libcflib/bootstrap_schema.py
libcflib/db.xsh
libcflib/environ.py
libcflib/harvest_pkgs.xsh
libcflib/harvester.py
libcflib/indexer.py
libcflib/jsonutils.py
libcflib/logger.py
libcflib/models.xsh
libcflib/preloader.py
libcflib/schemas.py
libcflib/tools.xsh
libcflib.egg-info/PKG-INFO
libcflib.egg-info/SOURCES.txt
libcflib.egg-info/dependency_links.txt
libcflib.egg-info/not-zip-safe
libcflib.egg-info/requires.txt
libcflib.egg-info/top_level.txt
libcflib/rest/__init__.py
libcflib/rest/__main__.py
libcflib/rest/handlers.py
libcflib/rest/main.py
libcflib/rest/request_handler.py