Metadata-Version: 1.1
Name: libcflib
Version: 0.0.8
Summary: Library Conda Forge Library
Home-page: https://github.com/regro/libcflib
Author: The Regro developers
Author-email: conda-forge@googlegroups.com
License: BSD 3-clause
Download-URL: https://github.com/ergs/conda-forge/zipball/0.0.8
Platform: UNKNOWN
Classifier: License :: OSI Approved
Classifier: Intended Audience :: Developers
Classifier: Programming Language :: Python
Classifier: Topic :: Utilities
